qthvym/.gitignore
qthvym/__init__.py
qthvym/passwordedit.py
qthvym/ui_helpers.py
qthvym/data/dfinity_logo.png
qthvym/data/hvym.png
qthvym/data/logo.png
qthvym/data/opus_logo.png
qthvym/data/spinner.gif
qthvym/data/stellar_logo.png
qthvym/data/style.qss
qthvym/data/xro_logo.png
qthvym/data/passwordedit/eye.svg
qthvym/data/passwordedit/hidden.svg
qthvym-0.17.dist-info/licenses/LICENSE
qthvym-0.17.dist-info/WHEEL
qthvym-0.17.dist-info/METADATA
qthvym-0.17.dist-info/RECORD
