Metadata-Version: 2.4
Name: qthvym
Version: 0.17
Summary: QT5 UI Elements For HVYM, By: Fibo Metavinci
Author-email: Fibo Metavinci <pszdw-75nat-5227i-bha5s-y7lai-pebdq-o2agp-3xho4-hd6z6-emxrd-nqe@dmail.ai>
Classifier: License :: OSI Approved :: MIT License
License-File: LICENSE
Requires-Dist: certifi>=2025.4.26
Requires-Dist: charset-normalizer>=3.4.2
Requires-Dist: docutils>=0.21.2
Requires-Dist: idna>=3.10
Requires-Dist: importlib_metadata>=8.6.1
Requires-Dist: Markdown>=3.7
Requires-Dist: packaging>=24.2
Requires-Dist: pillow>=11.1.0
Requires-Dist: pyperclip>=1.9.0
Requires-Dist: PyQt5>=5.15.11
Requires-Dist: PyQt5-Qt5>=5.15.2
Requires-Dist: PyQt5_sip>=12.17.0
Requires-Dist: qrcode>=8.0
Requires-Dist: QtPy>=2.4.2
Requires-Dist: requests>=2.32.3
Requires-Dist: tomli_w>=1.2.0
Requires-Dist: urllib3>=2.4.0
Requires-Dist: zipp>=3.21.0
Project-URL: Home, https://github.com/inviti8/QtHVYM
